[
    {
        "icon":"HiPhone",
        "title":"Free Call Support",
        "descrption":"Donec et venenatis libero. Fusceing dapibus pulvinar tincidunt. Proin maximus ipsum ut scelerisque."
    },
    {
        "icon":"HiPhone",
        "title":"Free Call Support",
        "descrption":"Donec et venenatis libero. Fusceing dapibus pulvinar tincidunt. Proin maximus ipsum ut scelerisque."
    },
    {
        "icon":"HiPhone",
        "title":"Free Call Support",
        "descrption":"Donec et venenatis libero. Fusceing dapibus pulvinar tincidunt. Proin maximus ipsum ut scelerisque."
    },
    {
        "icon":"HiPhone",
        "title":"Free Call Support",
        "descrption":"Donec et venenatis libero. Fusceing dapibus pulvinar tincidunt. Proin maximus ipsum ut scelerisque."
    },
    {
        "icon":"HiPhone",
        "title":"Free Call Support",
        "descrption":"Donec et venenatis libero. Fusceing dapibus pulvinar tincidunt. Proin maximus ipsum ut scelerisque."
    },
    {
        "icon":"HiPhone",
        "title":"Free Call Support",
        "descrption":"Donec et venenatis libero. Fusceing dapibus pulvinar tincidunt. Proin maximus ipsum ut scelerisque."
    }

]
